cdk_redisdb/__init__.py
cdk_redisdb/py.typed
cdk_redisdb/_jsii/__init__.py
cdk_redisdb/_jsii/cdk-redisdb@0.0.38.jsii.tgz
cdk_redisdb-0.0.38.dist-info/LICENSE
cdk_redisdb-0.0.38.dist-info/METADATA
cdk_redisdb-0.0.38.dist-info/WHEEL
cdk_redisdb-0.0.38.dist-info/top_level.txt
cdk_redisdb-0.0.38.dist-info/RECORD
